MANIFEST.in
README.md
pyproject.toml
setup.py
amuse_kepler_orbiters.egg-info/PKG-INFO
amuse_kepler_orbiters.egg-info/SOURCES.txt
amuse_kepler_orbiters.egg-info/dependency_links.txt
amuse_kepler_orbiters.egg-info/requires.txt
amuse_kepler_orbiters.egg-info/top_level.txt
src/amuse/community/kepler_orbiters/Makefile
src/amuse/community/kepler_orbiters/__init__.py
src/amuse/community/kepler_orbiters/_version.py
src/amuse/community/kepler_orbiters/interface.cc
src/amuse/community/kepler_orbiters/interface.py
src/amuse/community/kepler_orbiters/test_kepler.py
src/amuse/community/kepler_orbiters/src/Makefile
src/amuse/community/kepler_orbiters/src/common.h
src/amuse/community/kepler_orbiters/src/universal_kepler_solver.h
src/amuse/community/kepler_orbiters/src/universal_variable_kepler.c
src/amuse/community/kepler_orbiters/src/universal_variable_kepler.h
support/__init__.py
support/classifiers.py
support/config.py
support/generate_main.py
support/getsp.class
support/getsp.java
support/misc.py
support/setup_codes.py
support/version.py